dynamite/__init__.py
dynamite/enums.py
dynamite/utils.py
dynamite_streams-0.0.1.dist-info/LICENSE
dynamite_streams-0.0.1.dist-info/METADATA
dynamite_streams-0.0.1.dist-info/WHEEL
dynamite_streams-0.0.1.dist-info/top_level.txt
dynamite_streams-0.0.1.dist-info/RECORD
