Metadata-Version: 2.1
Name: dynamite-streams
Version: 0.0.1
Summary: A module to be used as an AWS Lambda function to keep postgres replicas of dynamodb tables.
Home-page: http://github.com/dbish/dynamite
Author: Dillon Hicks
Author-email: chronodynamic@gmail.com
License: Apache License Version 2
Platform: any
Classifier: Development Status :: 2 - Pre-Alpha
Classifier: Environment :: Web Environment
Classifier: Intended Audience :: Developers
Classifier: License :: OSI Approved :: Apache Software License
Classifier: Operating System :: OS Independent
Classifier: Programming Language :: Python :: 3
Classifier: Topic :: Database
Classifier: Topic :: Software Development :: Libraries :: Python Modules
Classifier: Topic :: Internet
Classifier: Topic :: System :: Archiving :: Mirroring
Requires-Python: >=3.7
Requires-Dist: boto3
Requires-Dist: sqlalchemy
Requires-Dist: pg8000
